mcp_android/__init__.py
mcp_android/__main__.py
mcp_android/server.py
mcp_android/tools.py
mcp_android/logs/AndroidControlServer_2025-05-30-18-10-27.txt
mcp_android/logs/AndroidControlServer_2025-05-30-18-10-39.txt
mcp_android/logs/AndroidControlServer_2025-05-30-18-11-01.txt
mcp_android/logs/AndroidControlServer_2025-05-30-18-33-14.txt
mcp_android/logs/AndroidControlServer_2025-05-30-18-33-54.txt
mcp_android/logs/AndroidControlServer_2025-05-30-18-33-55.txt
mcp_android/logs/AndroidControlServer_2025-05-30-18-53-24.txt
mcp_android/logs/AndroidControlServer_2025-06-03-16-59-12.txt
mcp_android/logs/AndroidControlServer_2025-06-03-18-36-21.txt
mcp_android/logs/AndroidControlServer_2025-06-03-18-36-22.txt
mcp_android/logs/AndroidControlServer_2025-06-05-10-11-37.txt
mcp_android/logs/AndroidControlServer_2025-06-05-10-12-44.txt
mcp_android/logs/AndroidControlServer_2025-06-06-11-18-53.txt
mcp_android/logs/AndroidControlServer_2025-06-06-11-18-54.txt
mcp_android/logs/AndroidControlServer_2025-06-10-16-30-49.txt
mcp_android/logs/AndroidControlServer_2025-06-10-16-31-14.txt
mcp_android/logs/AndroidControlServer_2025-06-10-16-33-07.txt
mcp_android/logs/AndroidControlServer_2025-06-11-13-39-57.txt
mcp_android/logs/AndroidControlServer_2025-06-11-13-40-18.txt
mcp_android/logs/AndroidControlServer_2025-06-11-19-45-38.txt
mcp_android/logs/AndroidControlServer_2025-06-11-19-50-33.txt
mcp_android/logs/AndroidControlServer_2025-06-11-19-51-15.txt
mcp_android/logs/AndroidControlServer_2025-06-12-11-11-38.txt
mcp_android/logs/AndroidControlServer_2025-06-12-15-16-46.txt
mcp_android/logs/AndroidControlServer_2025-06-16-13-37-37.txt
mcp_android/logs/AndroidControlServer_2025-06-17-16-54-51.txt
mcp_android/logs/AndroidControlServer_2025-07-11-09-55-05.txt
mcp_android/logs/AndroidControlServer_2025-07-30-10-19-45.txt
mcp_android/logs/AndroidControlServer_2025-07-30-10-19-46.txt
mcp_android/logs/AndroidControlServer_2025-07-30-10-20-30.txt
mcp_android-0.1.7.dist-info/METADATA
mcp_android-0.1.7.dist-info/WHEEL
mcp_android-0.1.7.dist-info/entry_points.txt
mcp_android-0.1.7.dist-info/RECORD
