Metadata-Version: 2.4
Name: mcp-android
Version: 0.1.7
Summary: A custom MCP tool for Android
Author-email: "chuanwen.peng" <chuanwen.peng@tcl.com>
Requires-Python: >=3.11
Requires-Dist: fastmcp>=2.5.2
Requires-Dist: mcp>=1.9.2
Requires-Dist: uiautomator2>=2.14.3
